<?xml version="1.0" encoding="UTF-8"?>
<import xmlns="http://resolver.nkp.cz/v4/">
    <!-- výtisk periodika -->
    <periodicalIssue>
        <titleInfo>
            <!-- název periodika (povinný údaj) -->
            <periodicalTitle>Rudé právo</periodicalTitle>
            <!-- název ročníku (svazku) -->
            <volumeTitle>ročník 1945</volumeTitle>
            <!-- název čísla (povinný údaj) -->
            <issueTitle>16.5.1945</issueTitle>
        </titleInfo>
        <!-- čČNB periodika -->
        <ccnb>cnb000431774</ccnb>
        <!-- ISSN periodika -->
        <issn>0032-6569</issn>
        <!-- jiný globální identifikátor periodika -->
        <otherId>SICI:TODO</otherId>
        <!-- druh dokumentu -->
        <documentType>ranní vydání novin</documentType>
        <!-- zda je dokument e-born, defaultně false -->
        <digitalBorn>false</digitalBorn>
        <!-- hlavní původce (autor/korporace/akce) -->
        <primaryOriginator type="CORPORATION">Komunistická strana Československa</primaryOriginator>
        <!-- další původce (např. ilustrátor nebo překladatel) -->
        <otherOriginator>Jan Ilustrator</otherOriginator>
        <!-- informace o publikování -->
        <publication>
        <!-- název vydavatele -->
            <publisher>Ústřední výbor KSČ</publisher>
            <!-- místo vydání -->
            <place>Praha</place>
            <!-- rok vydání -->
            <year>1945</year>
        </publication>
    </periodicalIssue>
    <digitalDocument>
        <!-- identifikátor archivátora -->
        <archiverId>3</archiverId>
        <!-- seznam identifikátorů v rámci registrátora -->
        <registrarScopeIdentifiers>
            <id type="OAI_harvester">1237</id>
            <id type="K4_pid">uuid:38bfc69d-1d10-4822-b7a4-c7531bb4aedj</id>
        </registrarScopeIdentifiers>
        <!-- čím/kým byla digitalizace financována 
             pro novou digitalizaci v rámci NDK zde bude vždy hodnota IOP-NDK
        -->
        <financed>norské fondy</financed>
        <!-- číslo zakázky, u nové digitalizace se nebude uvádět -->
        <contractNumber>123</contractNumber>
        <!-- technická metadata, která se vážou k ARCHIVNÍ verzi
             digitálního dokumentu -->
        <technicalMetadata>
            <!-- typ a verze formátu -->
            <format version="1.0">jpeg</format>
            <!-- rozsah (v počtu souborů) -->
            <extent>12 x jpeg2000;12 x mods-alto;1 x mods</extent>
            <!-- rozlišení nastavené na skeneru v dpi-->
            <resolution>
                <!-- horizontální -->
                <horizontal>1280</horizontal>
                <!-- vertikální -->
                <vertical>1024</vertical>
            </resolution>
            <!-- kompresní algoritmus a komprimační poměr -->
            <compression ratio="0.3">LZW</compression>
            <color>
                <!-- barevný model -->
                <model>RGB</model>
                <!-- bitová hloubka -->
                <depth>24</depth>
            </color>
            <!-- ICC profil -->
            <iccProfile>some ICC profile</iccProfile>
            <!-- realná velikost obrázků (něktěrého obrázku) v pixelech -->
            <pictureSize>
                <width>600</width>
                <height>1000</height>
            </pictureSize>
        </technicalMetadata>
    </digitalDocument>
</import>
